langchain_ray/__init__.py
langchain_ray/_modidx.py
langchain_ray/chains.py
langchain_ray/imports.py
langchain_ray/remote_utils.py
langchain_ray/utils.py
langchain_ray/api/__init__.py
langchain_ray/api/app.py
langchain_ray/api/app_deployment.py
langchain_ray/api/imports.py
langchain_ray/driver/__init__.py
langchain_ray/driver/ingress_driver.py
langchain_ray/driver/redis_kv_store.py
langchain_ray/indexing/__init__.py
langchain_ray/indexing/chains.py
langchain_ray/indexing/utils.py
langchain_ray/ner/__init__.py
langchain_ray/ner/chains.py
langchain_ray/ner/utils.py
langchain_ray/pdf/__init__.py
langchain_ray/pdf/chains.py
langchain_ray/pdf/ner.py
langchain_ray/pdf/utils.py
langchain_ray-0.0.12.dist-info/LICENSE
langchain_ray-0.0.12.dist-info/METADATA
langchain_ray-0.0.12.dist-info/WHEEL
langchain_ray-0.0.12.dist-info/entry_points.txt
langchain_ray-0.0.12.dist-info/top_level.txt
langchain_ray-0.0.12.dist-info/RECORD
