Metadata-Version: 2.1
Name: langchain-ray
Version: 0.0.12
Summary: LangChain leveraging Ray.
Home-page: https://github.com/HamzaFarhan/langchain_ray
Author: Hamza Farhan
Author-email: thehamza96@gmail.com
License: Apache Software License 2.0
Keywords: nbdev jupyter notebook python
Classifier: Development Status :: 4 - Beta
Classifier: Intended Audience :: Developers
Classifier: Natural Language :: English
Classifier: Programming Language :: Python :: 3.8
Classifier: Programming Language :: Python :: 3.9
Classifier: Programming Language :: Python :: 3.10
Classifier: License :: OSI Approved :: Apache Software License
Requires-Python: >=3.8
License-File: LICENSE
Requires-Dist: ray[air]
Requires-Dist: dreamai
Requires-Dist: langchain
Requires-Dist: transformers
Requires-Dist: pypdf
Requires-Dist: faiss-cpu
Requires-Dist: sentence-transformers
Requires-Dist: fastai
Requires-Dist: accelerate
Requires-Dist: demoji
Requires-Dist: clean-text
Requires-Dist: Unidecode
Requires-Dist: tabulate
Requires-Dist: redis
Requires-Dist: setfit
Provides-Extra: dev
